{"data":{"site":{"siteMetadata":{"author":{"name":"Pascal Precht","bio":"Hi, I'm Pascal and this is my blog.<br/>I mostly write about code.","photo":"/photo.jpg","contacts":{"email":"","telegram":"","twitter":"PascalPrecht","github":"PascalPrecht","rss":"","vkontakte":""}},"menu":[{"label":"Articles","path":"/"},{"label":"About","path":"/about"},{"label":"Books I like","path":"/favorite-books"}],"url":"https://pascalprecht.github.io","title":"Pascal Precht's Blog","subtitle":"This is my personal blog where I mostly write about code.","copyright":"© 2014 - 2020 Made without love.","disqusShortname":""}}}}